dwcahandler/__init__.py
dwcahandler/dwca/__init__.py
dwcahandler/dwca/base_dwca.py
dwcahandler/dwca/core_dwca.py
dwcahandler/dwca/dwca_factory.py
dwcahandler/dwca/dwca_meta.py
dwcahandler/dwca/eml.py
dwcahandler/dwca/terms/class-rowtype.csv
dwcahandler/dwca/terms/extension-register.csv
dwcahandler/dwca/terms/terms.csv
dwcahandler/dwca/terms.py
dwcahandler/scripts/update_terms.py
dwcahandler-1.1.0.dist-info/METADATA
dwcahandler-1.1.0.dist-info/WHEEL
dwcahandler-1.1.0.dist-info/entry_points.txt
dwcahandler-1.1.0.dist-info/licenses/LICENSE
dwcahandler-1.1.0.dist-info/RECORD
