Metadata-Version: 2.4
Name: dwcahandler
Version: 1.1.0
Summary: Python package to handle Darwin Core Archive (DwCA) operations. This includes creating a DwCA zip file from one or more csvs, reading a DwCA, merge two DwCAs, validate DwCA and delete records from DwCA based on one or more key columns
License: MPL-1.1
License-File: LICENSE
Author: Atlas of Living Australia data team
Author-email: support@ala.org.au
Maintainer: Atlas of Living Australia data team
Maintainer-email: support@ala.org.au
Requires-Python: >=3.9
Classifier: License :: OSI Approved :: Mozilla Public License 1.1 (MPL 1.1)
Classifier: Programming Language :: Python :: 3
Classifier: Programming Language :: Python :: 3.9
Classifier: Programming Language :: Python :: 3.10
Classifier: Programming Language :: Python :: 3.11
Classifier: Programming Language :: Python :: 3.12
Classifier: Programming Language :: Python :: 3.13
Classifier: Programming Language :: Python :: 3.14
Requires-Dist: flake8 (>=7.1.1,<8.0.0)
Requires-Dist: metapype (>=0.0.26,<0.0.27)
Requires-Dist: pandas (>=2.2.0,<3.0.0)
Requires-Dist: pytest (>=8.2.0,<9.0.0)
Requires-Dist: pytest-cov (>=6.1.1,<7.0.0)
Requires-Dist: pytest-mock (>=3.12.0,<4.0.0)
Requires-Dist: requests (>=2.32.0,<3.0.0)
Project-URL: Repository, https://github.com/AtlasOfLivingAustralia/dwcahandler
